rosa/__init__.py
rosa/prompts.py
rosa/rosa.py
rosa/tools/__init__.py
rosa/tools/calculation.py
rosa/tools/log.py
rosa/tools/ros1.py
rosa/tools/ros2.py
rosa/tools/system.py
turtle_agent/scripts/__init__.py
turtle_agent/scripts/help.py
turtle_agent/scripts/llm.py
turtle_agent/scripts/prompts.py
turtle_agent/scripts/turtle_agent.py
turtle_agent/scripts/tools/__init__.py
turtle_agent/scripts/tools/turtle.py
jpl_rosa-1.0.7.dist-info/LICENSE
jpl_rosa-1.0.7.dist-info/METADATA
jpl_rosa-1.0.7.dist-info/WHEEL
jpl_rosa-1.0.7.dist-info/top_level.txt
jpl_rosa-1.0.7.dist-info/RECORD
