Metadata-Version: 2.1
Name: jpl-rosa
Version: 1.0.7
Summary: ROSA: the Robot Operating System Agent
Author-email: Rob Royce <Rob.Royce@jpl.nasa.gov>
License: Apache License
Project-URL: Homepage, https://github.com/nasa-jpl/rosa
Project-URL: Bug Tracker, https://github.com/nasa-jpl/rosa/issues
Keywords: Robotics,Data Science,Machine Learning,Data Engineering,Data Infrastructure,Data Analysis
Classifier: Development Status :: 4 - Beta
Classifier: Environment :: Console
Classifier: Intended Audience :: Science/Research
Classifier: License :: OSI Approved :: Apache Software License
Classifier: Natural Language :: English
Classifier: Operating System :: Unix
Classifier: Programming Language :: Python :: 3
Classifier: Topic :: Scientific/Engineering
Classifier: Topic :: Scientific/Engineering :: Artificial Intelligence
Requires-Python: <4,>=3.9
License-File: LICENSE
Requires-Dist: PyYAML==6.0.1
Requires-Dist: python-dotenv>=1.0.1
Requires-Dist: langchain==0.3.2
Requires-Dist: langchain-community==0.3.1
Requires-Dist: langchain-core==0.3.9
Requires-Dist: langchain-openai==0.2.2
Requires-Dist: langchain-ollama==0.2.0
Requires-Dist: pydantic
Requires-Dist: pyinputplus
Requires-Dist: azure-identity
Requires-Dist: cffi
Requires-Dist: rich
Requires-Dist: pillow>=10.4.0
Requires-Dist: numpy>=1.26.4
